LICENSE
README.rst
readonly/__init__.py
readonly/readonly.py
readonly-0.1.2.dist-info/LICENSE
readonly-0.1.2.dist-info/WHEEL
readonly-0.1.2.dist-info/METADATA
readonly-0.1.2.dist-info/RECORD
