Metadata-Version: 2.1
Name: readonly
Version: 0.1.2
Summary: Make any module attributes read only.
Home-page: https://github.com/wiseaidev/readonly
License: GNU General Public License v3.0
Keywords: python,readonly
Author: Mahmoud Harmouch
Author-email: business@wiseai.dev
Requires-Python: >=3.9,<4.0
Classifier: Development Status :: 2 - Pre-Alpha
Classifier: Intended Audience :: Developers
Classifier: License :: Other/Proprietary License
Classifier: Natural Language :: English
Classifier: Programming Language :: Python :: 3
Classifier: Programming Language :: Python :: 3.9
Classifier: Programming Language :: Python :: 3.10
Classifier: Programming Language :: Python :: 3.11
Classifier: Programming Language :: Python :: 3
Classifier: Programming Language :: Python :: 3.10
Classifier: Programming Language :: Python :: 3.9
Project-URL: Repository, https://github.com/wiseaidev/readonly
